hpo_benchmarks/__init__.py
hpo_benchmarks/base.py
hpo_benchmarks/hpobench.py
hpo_benchmarks/hpolib.py
hpo_benchmarks/nasbench201.py
hpo_benchmarks/datasets/hpobench/australian.pkl
hpo_benchmarks/datasets/hpobench/blood_transfusion.pkl
hpo_benchmarks/datasets/hpobench/car.pkl
hpo_benchmarks/datasets/hpobench/credit_g.pkl
hpo_benchmarks/datasets/hpobench/kc1.pkl
hpo_benchmarks/datasets/hpobench/phoneme.pkl
hpo_benchmarks/datasets/hpobench/segment.pkl
hpo_benchmarks/datasets/hpobench/vehicle.pkl
hpo_benchmarks/datasets/hpolib/naval_propulsion.pkl
hpo_benchmarks/datasets/hpolib/parkinsons_telemonitoring.pkl
hpo_benchmarks/datasets/hpolib/protein_structure.pkl
hpo_benchmarks/datasets/hpolib/slice_localization.pkl
hpo_benchmarks/datasets/nasbench201/cifar10.pkl
hpo_benchmarks/datasets/nasbench201/cifar100.pkl
hpo_benchmarks/datasets/nasbench201/imagenet.pkl
simple_hpo_bench-0.2.0.dist-info/LICENSE
simple_hpo_bench-0.2.0.dist-info/METADATA
simple_hpo_bench-0.2.0.dist-info/WHEEL
simple_hpo_bench-0.2.0.dist-info/top_level.txt
simple_hpo_bench-0.2.0.dist-info/RECORD
